{
  "date": "2026-06-28",
  "client_keyword": "UPWORK_KICAD_PCB_SCHEMA_DESIGN",
  "role_keyword": "PCB_LAYOUT",
  "project_name": "KiCad PCB Board Schema and Design",
  "job_title": "KiCad PCB Board Schema and Design",
  "platform": "Upwork",
  "project_domain": "KiCad PCB layout, routing, and manufacturing package delivery for Raspberry Pi 4 carrier board",
  "key_features": "Complete mostly-finished schematic into layout-ready design, 100x80 mm 2/4-layer board planning, Raspberry Pi 4 carrier integration, Southco R4-EM rotary latch drive path, PN532 UART NFC connectivity, DFM-focused routing, manufacturing-ready output package",
  "company_name": "Bluetrace Technologies Pvt. Ltd.",
  "prepared_by": "A.R. Ansari",
  "budget_usd": "25/hr",
  "duration_label": "Hourly contract, less than 30 hrs/week",
  "planned_timeline": "1 to 3 months",
  "milestone_1_desc": "Schematic completion audit and layout constraint definition",
  "milestone_1_amount": "250",
  "milestone_1_time": "Week 1",
  "milestone_2_desc": "Component placement and stack-up strategy for 100x80 mm board",
  "milestone_2_amount": "400",
  "milestone_2_time": "Weeks 2-3",
  "milestone_3_desc": "Routing, power integrity checks, and interface validation",
  "milestone_3_amount": "450",
  "milestone_3_time": "Weeks 4-6",
  "milestone_4_desc": "Manufacturing package generation and release handoff",
  "milestone_4_amount": "300",
  "milestone_4_time": "Weeks 7-8",
  "doc_id": "BT-KICAD-RPI4-CARRIER",
  "version": "v1.0",
  "revision": "R0",
  "classification": "Client Shareable"
}

